lino_avanti/__init__.py
lino_avanti/lib/__init__.py
lino_avanti/lib/avanti/__init__.py
lino_avanti/lib/avanti/choicelists.py
lino_avanti/lib/avanti/help_texts.py
lino_avanti/lib/avanti/layouts.py
lino_avanti/lib/avanti/migrate.py
lino_avanti/lib/avanti/models.py
lino_avanti/lib/avanti/roles.py
lino_avanti/lib/avanti/settings.py
lino_avanti/lib/avanti/user_types.py
lino_avanti/lib/avanti/workflows.py
lino_avanti/lib/avanti/config/avanti/Client/final_report.weasy.html
lino_avanti/lib/avanti/fixtures/__init__.py
lino_avanti/lib/avanti/fixtures/demo.py
lino_avanti/lib/avanti/fixtures/demo2.py
lino_avanti/lib/avanti/fixtures/std.py
lino_avanti/lib/avanti/locale/django.pot
lino_avanti/lib/avanti/locale/de/LC_MESSAGES/django.mo
lino_avanti/lib/avanti/locale/de/LC_MESSAGES/django.po
lino_avanti/lib/avanti/locale/fr/LC_MESSAGES/django.mo
lino_avanti/lib/avanti/locale/fr/LC_MESSAGES/django.po
lino_avanti/lib/avanti/locale/nl/LC_MESSAGES/django.mo
lino_avanti/lib/avanti/locale/nl/LC_MESSAGES/django.po
lino_avanti/lib/cal/__init__.py
lino_avanti/lib/cal/models.py
lino_avanti/lib/cal/fixtures/__init__.py
lino_avanti/lib/cal/fixtures/demo2.py
lino_avanti/lib/cal/fixtures/std.py
lino_avanti/lib/contacts/__init__.py
lino_avanti/lib/contacts/models.py
lino_avanti/lib/contacts/fixtures/__init__.py
lino_avanti/lib/contacts/fixtures/demo.py
lino_avanti/lib/contacts/fixtures/std.py
lino_avanti/lib/contacts/management/__init__.py
lino_avanti/lib/contacts/management/commands/__init__.py
lino_avanti/lib/courses/__init__.py
lino_avanti/lib/courses/choicelists.py
lino_avanti/lib/courses/models.py
lino_avanti/lib/courses/ui.py
lino_avanti/lib/courses/workflows.py
lino_avanti/lib/courses/config/courses/Enrolment/Default.odt
lino_avanti/lib/courses/config/courses/Reminder/Default.odt
lino_avanti/lib/courses/config/courses/Reminder/body.html
lino_avanti/lib/courses/config/courses/Reminder/reminder.body.html
lino_avanti/lib/cv/__init__.py
lino_avanti/lib/cv/models.py
lino_avanti-25.3.1.dist-info/METADATA
lino_avanti-25.3.1.dist-info/WHEEL
lino_avanti-25.3.1.dist-info/licenses/COPYING
lino_avanti-25.3.1.dist-info/licenses/COPYING~
lino_avanti-25.3.1.dist-info/RECORD
